Metadata-Version: 2.1
Name: CustomTkWidgets
Version: 0.0.1
Summary: Custom widgets to make tkinter look better
Home-page: UNKNOWN
Author: Nihaal Nz
Author-email: nihaalnz@gmail.com
License: MIT
Keywords: tkinter
Platform: UNKNOWN
Classifier: Development Status :: 5 - Production/Stable
Classifier: Intended Audience :: Education
Classifier: Operating System :: Microsoft :: Windows :: Windows 10
Classifier: License :: OSI Approved :: MIT License
Classifier: Programming Language :: Python :: 3
